ipyfetch/__init__.py
ipyfetch/_version.py
ipyfetch/fetch.py
ipyfetch/static/extension.js
ipyfetch/static/index.js
ipyfetch/static/index.js.map
ipyfetch-0.1.3.data/data/etc/jupyter/nbconfig/notebook.d/ipyfetch.json
ipyfetch-0.1.3.data/data/share/jupyter/nbextensions/ipyfetch/extension.js
ipyfetch-0.1.3.data/data/share/jupyter/nbextensions/ipyfetch/index.js
ipyfetch-0.1.3.data/data/share/jupyter/nbextensions/ipyfetch/index.js.map
ipyfetch-0.1.3.dist-info/LICENSE
ipyfetch-0.1.3.dist-info/METADATA
ipyfetch-0.1.3.dist-info/WHEEL
ipyfetch-0.1.3.dist-info/top_level.txt
ipyfetch-0.1.3.dist-info/RECORD
